{
	"aliasName":"opinion2",
	"attributes":[
		{
			"accessLevel":"private",
			"allowNull":false,
			"associateListAttr":false,
			"attributeLength":50,
			"attributeType":{
				"source":"primitive",
				"type":"String",
				"value":""
			},
			"chName":"主键id",
			"dbFieldId":"ID",
			"description":"主键id",
			"engName":"id",
			"precision":"0",
			"primaryKey":true,
			"queryExpr":"T1.ID =  #{id}",
			"queryField":true,
			"queryMatchRule":"1",
			"queryRange_1":"",
			"queryRange_2":"",
			"relationId":"",
			"sortNo":1
		},
		{
			"accessLevel":"private",
			"allowNull":true,
			"associateListAttr":false,
			"attributeLength":50,
			"attributeType":{
				"source":"primitive",
				"type":"String",
				"value":""
			},
			"chName":"人员id",
			"dbFieldId":"PERSON_ID",
			"description":"人员id",
			"engName":"personId",
			"precision":"0",
			"primaryKey":false,
			"queryExpr":"T1.PERSON_ID =  #{personId}",
			"queryField":true,
			"queryMatchRule":"1",
			"relationId":"",
			"sortNo":2
		},
		{
			"accessLevel":"private",
			"allowNull":true,
			"associateListAttr":false,
			"attributeLength":1000,
			"attributeType":{
				"source":"primitive",
				"type":"String",
				"value":""
			},
			"chName":"常用意见",
			"dbFieldId":"OPINION",
			"description":"常用意见",
			"engName":"opinion",
			"precision":"0",
			"primaryKey":false,
			"queryExpr":"T1.OPINION =  #{opinion}",
			"queryField":true,
			"queryMatchRule":"1",
			"relationId":"",
			"sortNo":3
		},
		{
			"accessLevel":"private",
			"allowNull":true,
			"associateListAttr":false,
			"attributeLength":1,
			"attributeType":{
				"source":"primitive",
				"type":"int",
				"value":""
			},
			"chName":"是否全局控制",
			"dbFieldId":"ISGLOBALCTRL",
			"description":"是否全局控制",
			"engName":"isglobalctrl",
			"precision":"0",
			"primaryKey":false,
			"queryExpr":"T1.ISGLOBALCTRL =  #{isglobalctrl}",
			"queryField":true,
			"queryMatchRule":"1",
			"relationId":"",
			"sortNo":4
		},
		{
			"accessLevel":"private",
			"allowNull":true,
			"associateListAttr":false,
			"attributeLength":50,
			"attributeType":{
				"source":"primitive",
				"type":"String",
				"value":""
			},
			"chName":"工单id(单据id)",
			"dbFieldId":"WORK_ID",
			"description":"工单id(单据id)",
			"engName":"workId",
			"precision":"0",
			"primaryKey":false,
			"queryExpr":"T1.WORK_ID =  #{workId}",
			"queryField":true,
			"queryMatchRule":"1",
			"queryRange_1":"",
			"queryRange_2":"",
			"relationId":"",
			"sortNo":5
		},
		{
			"accessLevel":"private",
			"allowNull":true,
			"associateListAttr":false,
			"attributeLength":0,
			"attributeType":{
				"source":"otherEntityAttibute",
				"type":"String",
				"value":"com.comtop.carstorage.entity.Bizaccount.remark"
			},
			"chName":"refBizAccount",
			"dbFieldId":"",
			"defaultValue":"",
			"description":"refBizAccount com.comtop.carstorage.entity.Bizaccount.remark",
			"engName":"refBizAccount",
			"precision":"",
			"primaryKey":false,
			"queryExpr":"",
			"queryField":false,
			"queryMatchRule":"",
			"queryRange_1":"",
			"queryRange_2":"",
			"relationId":"",
			"sortNo":6
		}
	],
	"bizObjectIds":[],
	"chName":"cap流程常用意见",
	"classPattern":"common",
	"createTime":1467615728648,
	"createrId":"001",
	"createrName":"CAP超级管理员",
	"customSqlConditionEnable":false,
	"dbObjectId":"com.comtop.carstorage.table.CAP_COMMON_OPINION",
	"dbObjectName":"CAP_COMMON_OPINION",
	"description":"cap流程常用意见",
	"engName":"Opinion",
	"entityType":"biz_entity",
	"generateCode":true,
	"lstRelation":[],
	"methods":[{
		"accessLevel":"public",
		"aliasName":"relationBizAccount",
		"assoMethodName":"",
		"autoMethod":false,
		"chName":"relationBizAccount",
		"constraint":"",
		"description":"relationBizAccount java.util.List<com.comtop.carstorage.entity.Bizaccount>",
		"engName":"relationBizAccount",
		"exceptions":[],
		"expPerformance":"",
		"features":"",
		"methodId":"1467615737492",
		"methodSource":"entity",
		"methodType":"blank",
		"needCount":false,
		"needPagination":false,
		"parameters":[{
			"chName":"bizAccount",
			"dataType":{
				"source":"entity",
				"type":"entity",
				"value":"com.comtop.carstorage.entity.Bizaccount"
			},
			"description":"bizAccount",
			"engName":"bizAccount",
			"parameterId":"1467615763318",
			"sortNo":0
		}],
		"privateService":false,
		"returnType":{
			"generic":[{
				"generic":[],
				"source":"entity",
				"type":"entity",
				"value":"com.comtop.carstorage.entity.Bizaccount"
			}],
			"source":"collection",
			"type":"java.util.List",
			"value":"java.util.List<com.comtop.carstorage.entity.Bizaccount>"
		},
		"serviceEx":"none",
		"transaction":true
	}],
	"modelId":"com.comtop.carstorage.entity.Opinion",
	"modelName":"Opinion",
	"modelPackage":"com.comtop.carstorage",
	"modelType":"entity",
	"packageId":"BFCD9F0A57FF49E889803A071D076BF6",
	"parentEntityId":"com.comtop.cap.runtime.base.entity.CapBase"
}