{
	"createTime":1467706603437,
	"metadataPageConfigModelId":"pageTemplate.oldPageConfigTmp.pageConfig.simpleModule",
	"metadataValue":{
		"editComponentList":[{
			"editGridAreaList":[{
				"area":"editGridCodeArea",
				"entityId":"com.comtop.tablerelation.entity.MmReceiptNoticeItem",
				"id":"editGrid_27253275503244197",
				"includeFileList":[
					{
						"defaultReference":false,
						"fileName":"dictionary",
						"filePath":"/cap/rt/common/cui/js/cui.extend.dictionary.js",
						"fileType":"js"
					},
					{
						"defaultReference":false,
						"fileName":"choose",
						"filePath":"/top/sys/usermanagement/orgusertag/js/choose.js",
						"fileType":"js"
					},
					{
						"defaultReference":false,
						"fileName":"engine",
						"filePath":"/cap/dwr/engine.js",
						"fileType":"js"
					},
					{
						"defaultReference":false,
						"fileName":"util",
						"filePath":"/cap/dwr/util.js",
						"fileType":"js"
					},
					{
						"defaultReference":false,
						"fileName":"ChooseAction",
						"filePath":"/top/sys/dwr/interface/ChooseAction.js",
						"fileType":"js"
					},
					{
						"defaultReference":false,
						"fileName":"choose",
						"filePath":"/top/sys/usermanagement/orgusertag/css/choose.css",
						"fileType":"css"
					}
				],
				"options":{
					"columns":"[{\"name\":\"合同编号\",\"bindName\":\"contractCode\"},{\"name\":\"采购单号\",\"bindName\":\"purchaseId\"},{\"name\":\"项目名称\",\"bindName\":\"projectName\"},{\"name\":\"单项工程名称\",\"bindName\":\"subprojectName\"},{\"name\":\"物资名称\",\"bindName\":\"materialName\"},{\"name\":\"计量单位\",\"bindName\":\"unitName\"},{\"name\":\"仓管员\",\"bindName\":\"warehouseManager\"},{\"name\":\"到货方式\",\"bindName\":\"deliverType\",\"render\":\"actionlibrary.bestPracticeAction.gridAction.action.gridDicRender\"}]",
					"databind":"editEntity.relationItemRelation",
					"edittype":"{\"contractCode\":{\"uitype\":\"Input\"},\"purchaseId\":{\"uitype\":\"Input\"},\"projectName\":{\"uitype\":\"Input\"},\"subprojectName\":{\"uitype\":\"Input\"},\"materialName\":{\"uitype\":\"Input\"},\"unitName\":{\"uitype\":\"Input\"},\"warehouseManager\":{\"uitype\":\"ChooseUser\",\"idName\":\"warehouseManagerId\",\"valueName\":\"warehouseManager\",\"databind\":\"warehouseManagerIdChooseUser\",\"thrdui\":true},\"deliverType\":{\"uitype\":\"PullDown\",\"dictionary\":\"deliverType\",\"datasource\":\"\"}}",
					"extras":"{\"entityId\":\"com.comtop.tablerelation.entity.MmReceiptNoticeItem\",\"tableHeader\":\"[{\\\"customHeaderId\\\":\\\"contractCode\\\",\\\"name\\\":\\\"合同编号\\\",\\\"bindName\\\":\\\"contractCode\\\",\\\"level\\\":1,\\\"indent\\\":\\\"\\\",\\\"format\\\":\\\"\\\",\\\"edittype\\\":{\\\"data\\\":{\\\"uitype\\\":\\\"Input\\\"}},\\\"check\\\":true,\\\"width\\\":\\\"\\\"},{\\\"customHeaderId\\\":\\\"purchaseId\\\",\\\"name\\\":\\\"采购单号\\\",\\\"bindName\\\":\\\"purchaseId\\\",\\\"level\\\":1,\\\"indent\\\":\\\"\\\",\\\"format\\\":\\\"\\\",\\\"edittype\\\":{\\\"data\\\":{\\\"uitype\\\":\\\"Input\\\"}},\\\"check\\\":false,\\\"width\\\":\\\"\\\"},{\\\"customHeaderId\\\":\\\"projectName\\\",\\\"name\\\":\\\"项目名称\\\",\\\"bindName\\\":\\\"projectName\\\",\\\"level\\\":1,\\\"indent\\\":\\\"\\\",\\\"format\\\":\\\"\\\",\\\"edittype\\\":{\\\"data\\\":{\\\"uitype\\\":\\\"Input\\\"}},\\\"check\\\":false,\\\"width\\\":\\\"\\\"},{\\\"customHeaderId\\\":\\\"subprojectName\\\",\\\"name\\\":\\\"单项工程名称\\\",\\\"bindName\\\":\\\"subprojectName\\\",\\\"level\\\":1,\\\"indent\\\":\\\"\\\",\\\"format\\\":\\\"\\\",\\\"edittype\\\":{\\\"data\\\":{\\\"uitype\\\":\\\"Input\\\"}},\\\"check\\\":false,\\\"width\\\":\\\"\\\"},{\\\"customHeaderId\\\":\\\"materialName\\\",\\\"name\\\":\\\"物资名称\\\",\\\"bindName\\\":\\\"materialName\\\",\\\"level\\\":1,\\\"indent\\\":\\\"\\\",\\\"format\\\":\\\"\\\",\\\"edittype\\\":{\\\"data\\\":{\\\"uitype\\\":\\\"Input\\\",\\\"validate\\\":\\\"\\\",\\\"maxlength\\\":\\\"\\\",\\\"emptytext\\\":\\\"\\\",\\\"mask\\\":\\\"\\\",\\\"maskoptions\\\":\\\"\\\",\\\"width\\\":\\\"\\\",\\\"maxheight\\\":\\\"\\\",\\\"label\\\":\\\"\\\",\\\"id\\\":\\\"\\\",\\\"name\\\":\\\"\\\"},\\\"propertiesType\\\":{}},\\\"check\\\":false,\\\"width\\\":\\\"\\\"},{\\\"customHeaderId\\\":\\\"unitName\\\",\\\"name\\\":\\\"计量单位\\\",\\\"bindName\\\":\\\"unitName\\\",\\\"level\\\":1,\\\"indent\\\":\\\"\\\",\\\"format\\\":\\\"\\\",\\\"edittype\\\":{\\\"data\\\":{\\\"uitype\\\":\\\"Input\\\",\\\"validate\\\":\\\"\\\",\\\"maxlength\\\":\\\"\\\",\\\"emptytext\\\":\\\"\\\",\\\"mask\\\":\\\"\\\",\\\"maskoptions\\\":\\\"\\\",\\\"width\\\":\\\"\\\",\\\"maxheight\\\":\\\"\\\",\\\"label\\\":\\\"\\\",\\\"id\\\":\\\"\\\",\\\"name\\\":\\\"\\\"},\\\"propertiesType\\\":{}},\\\"check\\\":false,\\\"width\\\":\\\"\\\"},{\\\"customHeaderId\\\":\\\"warehouseManager\\\",\\\"name\\\":\\\"仓管员\\\",\\\"bindName\\\":\\\"warehouseManager\\\",\\\"level\\\":1,\\\"indent\\\":\\\"\\\",\\\"format\\\":\\\"\\\",\\\"edittype\\\":{\\\"data\\\":{\\\"uitype\\\":\\\"ChooseUser\\\",\\\"idName\\\":\\\"warehouseManagerId\\\",\\\"valueName\\\":\\\"warehouseManager\\\",\\\"opts\\\":\\\"\\\",\\\"validate\\\":\\\"\\\",\\\"orgStructureId\\\":\\\"\\\",\\\"rootId\\\":\\\"\\\",\\\"defaultOrgId\\\":\\\"\\\",\\\"formName\\\":\\\"\\\",\\\"maxLength\\\":\\\"\\\",\\\"winType\\\":\\\"\\\",\\\"width\\\":\\\"\\\",\\\"height\\\":\\\"\\\",\\\"id\\\":\\\"\\\",\\\"name\\\":\\\"\\\",\\\"label\\\":\\\"\\\",\\\"databind\\\":\\\"warehouseManagerIdChooseUser\\\"},\\\"propertiesType\\\":{}},\\\"check\\\":false,\\\"width\\\":\\\"\\\",\\\"render\\\":\\\"\\\"},{\\\"customHeaderId\\\":\\\"deliverType\\\",\\\"name\\\":\\\"到货方式\\\",\\\"bindName\\\":\\\"deliverType\\\",\\\"level\\\":1,\\\"indent\\\":\\\"\\\",\\\"format\\\":\\\"\\\",\\\"edittype\\\":{\\\"data\\\":{\\\"uitype\\\":\\\"PullDown\\\",\\\"dictionary\\\":\\\"deliverType\\\",\\\"validate\\\":\\\"\\\",\\\"enumdata\\\":\\\"\\\",\\\"datasource\\\":\\\"\\\",\\\"empty_text\\\":\\\"\\\",\\\"select\\\":\\\"\\\",\\\"filter_fields\\\":\\\"\\\",\\\"value_field\\\":\\\"\\\",\\\"label_field\\\":\\\"\\\",\\\"width\\\":\\\"\\\",\\\"height\\\":\\\"\\\",\\\"value\\\":\\\"\\\",\\\"label\\\":\\\"\\\",\\\"id\\\":\\\"\\\",\\\"name\\\":\\\"\\\"},\\\"propertiesType\\\":{}},\\\"render\\\":\\\"actionlibrary.bestPracticeAction.gridAction.action.gridDicRender\\\",\\\"check\\\":false,\\\"width\\\":\\\"\\\"}]\"}",
					"primarykey":"id"
				}
			}],
			"entityAlias":"editEntity",
			"entityId":"com.comtop.tablerelation.entity.MmReceiptNotice",
			"formAreaList":[{
				"area":"editFormCodeArea",
				"col":2,
				"id":"form_16227779650749028",
				"rowList":[
					{
						"cname":"制单人",
						"colspan":1,
						"componentModelId":"uicomponent.expand.component.chooseUser",
						"id":"creator",
						"options":{
							"databind":"editEntity.creatorIdChooseUser",
							"idName":"editEntity.creatorId",
							"uitype":"ChooseUser",
							"valueName":"editEntity.creator"
						}
					},
					{
						"cname":"制单时间",
						"colspan":1,
						"componentModelId":"uicomponent.common.component.calender",
						"id":"createDate",
						"options":{
							"databind":"editEntity.createDate",
							"uitype":"Calender"
						}
					},
					{
						"cname":"供应商名称",
						"colspan":1,
						"componentModelId":"uicomponent.expand.component.chooseOrg",
						"id":"vendorName",
						"options":{
							"databind":"editEntity.vendorIdChooseOrg",
							"idName":"editEntity.vendorId",
							"uitype":"ChooseOrg",
							"valueName":"editEntity.vendorName"
						}
					},
					{
						"cname":"送货仓库名称",
						"colspan":1,
						"componentModelId":"uicomponent.common.component.input",
						"id":"warehouseName",
						"options":{
							"databind":"editEntity.warehouseName",
							"uitype":"Input",
							"validate":"[{\"type\":\"length\",\"rule\":{\"max\":100,\"maxm\":\"送货仓库名称长度不能大于100个字符\"}}]"
						}
					},
					{
						"cname":"收货联系人",
						"colspan":1,
						"componentModelId":"uicomponent.expand.component.chooseUser",
						"id":"receiver",
						"options":{
							"databind":"editEntity.receiverIdChooseUser",
							"idName":"editEntity.receiverId",
							"uitype":"ChooseUser",
							"valueName":"editEntity.receiver"
						}
					},
					{
						"cname":"状态",
						"colspan":1,
						"componentModelId":"uicomponent.common.component.pullDown",
						"id":"status",
						"options":{
							"databind":"editEntity.status",
							"dictionary":"status",
							"uitype":"PullDown"
						}
					},
					{
						"cname":"备注",
						"colspan":1,
						"componentModelId":"uicomponent.common.component.textarea",
						"id":"remark",
						"options":{
							"databind":"editEntity.remark",
							"uitype":"Textarea",
							"validate":"[{\"type\":\"length\",\"rule\":{\"max\":400,\"maxm\":\"备注长度不能大于400个字符\"}}]"
						}
					}
				]
			}],
			"groupingBarList":[],
			"id":"editArea",
			"subComponentLayoutSortList":[
				"form_16227779650749028",
				"editGrid_27253275503244197"
			]
		}],
		"entityComponentList":[{
			"id":"entityId",
			"rowList":[{
				"chName":"到货通知",
				"engName":"MmReceiptNotice",
				"modelId":"com.comtop.tablerelation.entity.MmReceiptNotice",
				"suffix":"editEntity"
			}]
		}],
		"gridComponentList":[{
			"area":"listCodeArea",
			"areaId":"areaId_listArea",
			"entityAlias":"editEntity",
			"entityId":"com.comtop.tablerelation.entity.MmReceiptNotice",
			"id":"listArea",
			"includeFileList":[],
			"options":{
				"columns":"[{\"name\":\"到货通知单ID\",\"bindName\":\"id\"},{\"name\":\"制单人\",\"bindName\":\"creator\"},{\"name\":\"制单时间\",\"bindName\":\"createDate\",\"format\":\"yyyy-MM-dd\"},{\"name\":\"供应商名称\",\"bindName\":\"vendorName\"},{\"name\":\"状态\",\"bindName\":\"status\",\"render\":\"actionlibrary.bestPracticeAction.gridAction.action.gridDicRender\"},{\"name\":\"备注\",\"bindName\":\"remark\"}]",
				"extras":"{\"entityId\":\"com.comtop.tablerelation.entity.MmReceiptNotice\",\"tableHeader\":\"[{\\\"customHeaderId\\\":\\\"id\\\",\\\"name\\\":\\\"到货通知单ID\\\",\\\"bindName\\\":\\\"id\\\",\\\"level\\\":1,\\\"indent\\\":\\\"\\\",\\\"format\\\":\\\"\\\",\\\"check\\\":true,\\\"width\\\":\\\"\\\"},{\\\"customHeaderId\\\":\\\"creator\\\",\\\"name\\\":\\\"制单人\\\",\\\"bindName\\\":\\\"creator\\\",\\\"level\\\":1,\\\"indent\\\":\\\"\\\",\\\"format\\\":\\\"\\\",\\\"check\\\":false,\\\"width\\\":\\\"\\\"},{\\\"customHeaderId\\\":\\\"createDate\\\",\\\"name\\\":\\\"制单时间\\\",\\\"bindName\\\":\\\"createDate\\\",\\\"level\\\":1,\\\"indent\\\":\\\"\\\",\\\"format\\\":\\\"yyyy-MM-dd\\\",\\\"check\\\":false,\\\"width\\\":\\\"\\\"},{\\\"customHeaderId\\\":\\\"vendorName\\\",\\\"name\\\":\\\"供应商名称\\\",\\\"bindName\\\":\\\"vendorName\\\",\\\"level\\\":1,\\\"indent\\\":\\\"\\\",\\\"format\\\":\\\"\\\",\\\"check\\\":false,\\\"width\\\":\\\"\\\"},{\\\"customHeaderId\\\":\\\"status\\\",\\\"name\\\":\\\"状态\\\",\\\"bindName\\\":\\\"status\\\",\\\"level\\\":1,\\\"indent\\\":\\\"\\\",\\\"format\\\":\\\"\\\",\\\"render\\\":\\\"actionlibrary.bestPracticeAction.gridAction.action.gridDicRender\\\",\\\"check\\\":false,\\\"width\\\":\\\"\\\"},{\\\"customHeaderId\\\":\\\"remark\\\",\\\"name\\\":\\\"备注\\\",\\\"bindName\\\":\\\"remark\\\",\\\"level\\\":1,\\\"indent\\\":\\\"\\\",\\\"format\\\":\\\"\\\",\\\"check\\\":false,\\\"render\\\":\\\"\\\",\\\"width\\\":\\\"\\\"}]\"}",
				"primarykey":"id"
			}
		}],
		"hiddenComponentList":[{
			"id":"parentId",
			"name":"parentId",
			"value":"5B07EBD2ABA1417DBA668A9A9EE859C4"
		}],
		"inputComponentList":[
			{
				"id":"modelName",
				"name":"modelName",
				"value":"tableRelation"
			},
			{
				"id":"cname",
				"name":"cname",
				"value":"主从表"
			}
		],
		"menuComponentList":[{
			"id":"parentName",
			"name":"parentName",
			"value":"主从表应用"
		}],
		"queryComponentList":[{
			"entityAlias":"editEntity",
			"entityId":"com.comtop.tablerelation.entity.MmReceiptNotice",
			"fixedQueryAreaList":[{
				"area":"queryFixedCodeArea",
				"areaId":"areaId_queryFixedCodeArea",
				"col":2,
				"id":"uiid_5687605454768363",
				"rowList":[
					{
						"cname":"到货通知单ID",
						"colspan":1,
						"componentModelId":"uicomponent.common.component.input",
						"id":"id",
						"options":{
							"databind":"editEntity.id",
							"uitype":"Input",
							"validate":"[{\"type\":\"length\",\"rule\":{\"max\":36,\"maxm\":\"到货通知单ID长度不能大于36个字符\"}}]"
						}
					},
					{
						"cname":"制单人",
						"colspan":1,
						"componentModelId":"uicomponent.expand.component.chooseUser",
						"id":"creator",
						"options":{
							"databind":"editEntity.creatorIdChooseUser",
							"idName":"editEntity.creatorId",
							"uitype":"ChooseUser",
							"valueName":"editEntity.creator"
						}
					},
					{
						"cname":"制单时间",
						"colspan":1,
						"componentModelId":"uicomponent.common.component.calender",
						"id":"createDate",
						"options":{
							"databind":"editEntity.createDate",
							"uitype":"Calender"
						}
					},
					{
						"cname":"供应商名称",
						"colspan":1,
						"componentModelId":"uicomponent.expand.component.chooseOrg",
						"id":"vendorName",
						"options":{
							"databind":"editEntity.vendorIdChooseOrg",
							"idName":"editEntity.vendorId",
							"uitype":"ChooseOrg",
							"valueName":"editEntity.vendorName"
						}
					}
				]
			}],
			"id":"queryArea",
			"moreQueryAreaList":[{
				"area":"queryMoreCodeArea",
				"areaId":"areaId_queryMoreCodeArea",
				"col":2,
				"id":"uiid_31616758107041406",
				"rowList":[
					{
						"cname":"状态",
						"colspan":2,
						"componentModelId":"uicomponent.common.component.pullDown",
						"id":"status",
						"options":{
							"databind":"editEntity.status",
							"dictionary":"status",
							"uitype":"PullDown"
						}
					},
					{
						"cname":"备注",
						"colspan":2,
						"componentModelId":"uicomponent.common.component.textarea",
						"id":"remark",
						"options":{
							"databind":"editEntity.remark",
							"uitype":"Textarea",
							"validate":"[{\"type\":\"length\",\"rule\":{\"max\":400,\"maxm\":\"备注长度不能大于400个字符\"}}]"
						}
					}
				]
			}]
		}]
	},
	"modelId":"com.comtop.tablerelation.metadataGenerate.tableRelation",
	"modelName":"tableRelation",
	"modelPackage":"com.comtop.tablerelation",
	"modelType":"metadataGenerate"
}