{
	"attributes":[
		{
			"accessLevel":"private",
			"allowNull":false,
			"associateListAttr":false,
			"attributeLength":40,
			"attributeType":{
				"source":"primitive",
				"type":"String",
				"value":""
			},
			"chName":"主键",
			"content":"",
			"dbFieldId":"ROOMID",
			"description":"主键",
			"endRange":"",
			"engName":"roomid",
			"errorInfo":"",
			"precision":"0",
			"primaryKey":true,
			"queryExpr":"T1.ROOMID =  #{roomid}",
			"queryField":true,
			"queryMatchRule":"1",
			"queryRange_1":"",
			"queryRange_2":"",
			"relationId":"",
			"sortNo":1,
			"startRange":""
		},
		{
			"accessLevel":"private",
			"allowNull":true,
			"associateListAttr":false,
			"attributeLength":40,
			"attributeType":{
				"source":"primitive",
				"type":"String",
				"value":""
			},
			"chName":"会议室地址",
			"dbFieldId":"ADDRESS",
			"description":"会议室地址",
			"engName":"address",
			"precision":"0",
			"primaryKey":false,
			"queryExpr":"T1.ADDRESS =  #{address}",
			"queryField":true,
			"queryMatchRule":"1",
			"relationId":"",
			"sortNo":2
		},
		{
			"accessLevel":"private",
			"allowNull":true,
			"associateListAttr":false,
			"attributeLength":40,
			"attributeType":{
				"source":"primitive",
				"type":"String",
				"value":""
			},
			"chName":"会议室规模",
			"dbFieldId":"FSIZE",
			"description":"会议室规模",
			"engName":"fsize",
			"precision":"0",
			"primaryKey":false,
			"queryExpr":"T1.FSIZE =  #{fsize}",
			"queryField":true,
			"queryMatchRule":"1",
			"relationId":"",
			"sortNo":3
		},
		{
			"accessLevel":"private",
			"allowNull":true,
			"associateListAttr":false,
			"attributeLength":1000,
			"attributeType":{
				"source":"primitive",
				"type":"String",
				"value":""
			},
			"chName":"备注",
			"dbFieldId":"FDESC",
			"description":"备注",
			"engName":"fdesc",
			"precision":"0",
			"primaryKey":false,
			"queryExpr":"T1.FDESC =  #{fdesc}",
			"queryField":true,
			"queryMatchRule":"1",
			"relationId":"",
			"sortNo":4
		},
		{
			"accessLevel":"private",
			"allowNull":true,
			"associateListAttr":false,
			"attributeLength":40,
			"attributeType":{
				"source":"primitive",
				"type":"String",
				"value":""
			},
			"chName":"会议室编码",
			"dbFieldId":"FNUMBER",
			"description":"会议室编码",
			"engName":"fnumber",
			"precision":"0",
			"primaryKey":false,
			"queryExpr":"T1.FNUMBER =  #{fnumber}",
			"queryField":true,
			"queryMatchRule":"1",
			"relationId":"",
			"sortNo":5
		},
		{
			"accessLevel":"private",
			"allowNull":true,
			"associateListAttr":false,
			"attributeLength":40,
			"attributeType":{
				"source":"primitive",
				"type":"String",
				"value":""
			},
			"chName":"会议室名称",
			"dbFieldId":"NAME",
			"description":"会议室名称",
			"engName":"name",
			"precision":"0",
			"primaryKey":false,
			"queryExpr":"T1.NAME =  #{name}",
			"queryField":true,
			"queryMatchRule":"1",
			"relationId":"",
			"sortNo":6
		},
		{
			"accessLevel":"private",
			"allowNull":true,
			"associateListAttr":false,
			"attributeLength":7,
			"attributeType":{
				"source":"primitive",
				"type":"java.sql.Timestamp",
				"value":""
			},
			"chName":"lastupdatedate",
			"content":"",
			"dbFieldId":"LASTUPDATEDATE",
			"description":"",
			"endRange":"",
			"engName":"lastupdatedate",
			"errorInfo":"",
			"precision":"0",
			"primaryKey":false,
			"queryExpr":"T1.LASTUPDATEDATE =  #{lastupdatedate}",
			"queryField":true,
			"queryMatchRule":"1",
			"queryRange_1":"",
			"queryRange_2":"",
			"relationId":"",
			"sortNo":7,
			"startRange":""
		}
	],
	"bizObjectIds":[],
	"chName":"会议室",
	"classPattern":"common",
	"createTime":1454231446073,
	"createrId":"001",
	"createrName":"CAP超级管理员",
	"dbObjectId":"com.comtop.meeting.table.OMS_DEMO_XC_MEETINGROOM",
	"dbObjectName":"OMS_DEMO_XC_MEETINGROOM",
	"description":"会议室",
	"engName":"XcMeetingroom",
	"entityType":"biz_entity",
	"generateCode":true,
	"lstRelation":[],
	"methods":[
		{
			"accessLevel":"public",
			"assoMethodName":"",
			"autoMethod":false,
			"chName":"测试级联",
			"constraint":"",
			"description":"测试级联",
			"engName":"testJL",
			"exceptions":[],
			"expPerformance":"",
			"features":"",
			"lstCascadeAttribute":[],
			"methodId":"1456109533432",
			"methodOperateType":"query",
			"methodSource":"entity",
			"methodType":"cascade",
			"needCount":false,
			"needPagination":false,
			"parameters":[{
				"chName":"查询的实体Id",
				"dataType":{
					"source":"primitive",
					"type":"String"
				},
				"description":"查询的实体Id",
				"engName":"entityId",
				"parameterId":"1456109607723",
				"sortNo":0
			}],
			"privateService":false,
			"returnType":{
				"source":"entity",
				"type":"entity",
				"value":"com.comtop.meeting.entity.XcMeetingroom"
			},
			"serviceEx":"none",
			"transaction":true
		},
		{
			"accessLevel":"public",
			"assoMethodName":"",
			"autoMethod":false,
			"chName":"测试自定义SQL",
			"constraint":"",
			"description":"测试自定义SQL",
			"engName":"testSQL",
			"exceptions":[],
			"expPerformance":"",
			"features":"",
			"methodId":"1456110093718",
			"methodOperateType":"query",
			"methodSource":"entity",
			"methodType":"userDefinedSQL",
			"needCount":false,
			"needPagination":false,
			"parameters":[{
				"chName":"查询的实体Id",
				"dataType":{
					"source":"primitive",
					"type":"String"
				},
				"description":"查询的实体Id",
				"engName":"entityId",
				"parameterId":"1456110107029",
				"sortNo":0
			}],
			"privateService":false,
			"returnType":{
				"source":"entity",
				"type":"entity",
				"value":"com.comtop.meeting.entity.XcMeetingroom"
			},
			"serviceEx":"none",
			"transaction":true,
			"userDefinedSQL":{
				"parameterType":"String",
				"queryParams":[],
				"querySQL":"select * from oms_demo_xc_meetingroom",
				"resultType":"com.comtop.meeting.model.XcMeetingroomVO",
				"returnResult":[],
				"sortSQL":"order by lastupdatedate desc"
			}
		},
		{
			"accessLevel":"public",
			"assoMethodName":"",
			"autoMethod":false,
			"chName":"测试",
			"constraint":"",
			"description":"11",
			"engName":"test",
			"exceptions":[],
			"expPerformance":"",
			"features":"",
			"methodId":"1458616094516",
			"methodSource":"entity",
			"methodType":"blank",
			"needCount":false,
			"needPagination":false,
			"parameters":[],
			"privateService":false,
			"returnType":{
				"source":"primitive",
				"type":"String"
			},
			"serviceEx":"none",
			"transaction":true
		}
	],
	"modelId":"com.comtop.meeting.entity.XcMeetingroom",
	"modelName":"XcMeetingroom",
	"modelPackage":"com.comtop.meeting",
	"modelType":"entity",
	"packageId":"DEA6EA3F06F3445EB038D1E6E761C9FE",
	"parentEntityId":"com.comtop.cap.runtime.base.entity.CapWorkflow",
	"processId":"Pro3365008954395"
}