<basic src="page.txt" name="获取单元格内容" type="testStepDefinitions.basics.basic.get_table_cell" icon="icon-cog-wheel-silhouette" group="pageOpt" desc="获取单元格内容" definition="get_table_cell">
    <createTime>1469606781466</createTime>
    <modelId>testStepDefinitions.basics.basic.get_table_cell</modelId>
    <modelName>get_table_cell</modelName>
    <modelPackage>testStepDefinitions.basics</modelPackage>
    <modelType>basic</modelType>
    <arg valueType="String" required="true" name="table_locator" desc="表定位">
        <ctrl type="Input">
            <options><![CDATA[
            {
                'id': 'table_locator',
                'name': 'table_locator'
            }
]]></options>
        </ctrl>
        <help>表定位</help>
    </arg>
    <arg valueType="String" required="true" name="row" desc="行定位">
        <ctrl type="Input">
            <options><![CDATA[
            {
                'id': 'row',
                'name': 'row'
            }
]]></options>
        </ctrl>
        <help>行定位</help>
    </arg>
    <arg valueType="String" required="true" name="column" desc="列定位">
        <ctrl type="Input">
            <options><![CDATA[
            {
                'id': 'column',
                'name': 'column'
            }
]]></options>
        </ctrl>
        <help>列定位</help>
    </arg>
    <help><![CDATA[获取单元格内容]]></help>
    <lib>ComtopLibrary.py</lib>
    <macro><![CDATA[获取单元格内容    ${table_locator}    ${row}    ${column}    #${desc}]]></macro>
    <res>element.txt</res>
</basic>
